<root>
	<styles>
	    <include src="s2r://panorama/styles/dota_card_game_styles.vcss_c" />
		<include src="s2r://panorama/styles/card/card_face_decal.vcss_c" />
	</styles>

	<snippets>
		<snippet name="StatusModifier">
			<Panel class="ModifierContainer">
				<Panel class="ModifierType" />
			</Panel>
		</snippet>
	</snippets>
		<Panel class="CardFaceDecalContainer">
			<Panel id="AllegianceGlowTop"/>
			<Panel id="AllegianceGlowBottom"/>
			<Panel id="CardStatusContainer" />
		</Panel>
</root>
