<root>
	<styles>
		<include src="s2r://panorama/styles/gamestyles.vcss_c" />
		<include src="s2r://panorama/styles/dashboard/dcg_db_friend.vcss_c" />
	</styles>

	<DCGFriend>

		<Panel id="FriendImagePanel">

			<Panel id="FriendImage">
				<Panel id="EmptyPanel" />
				<DCGAvatarImage id="FriendAvatarImage" lazy="true" />
			</Panel>

			<Panel id="PartyLeaderOverlay" hittest="false" />
		</Panel>

		<Panel id="FriendDetails">
			<Panel id="FriendNameContainer">
				<Panel id="LobbyLeaderIcon" />
				<DCGUserName id="FriendName" />
			</Panel>
			<Panel class="LeftRightFlow">
				<DCGUserName id="FriendNickname" />
				<DCGUserRichPresence id="FriendRichPresence" />
			</Panel>			
			
		</Panel>

	</DCGFriend>

</root>
